{
  "page": {
    "sections": [
      {
        "sectionName": "GRID",
        "columnNum": "12",
        "autoFill": true,
        "autoFit": false,
        "rows": [
          {
            "value": 1,
            "unit": "fr"
          },
          {
            "value": 2,
            "unit": "fr"
          },
          {
            "value": 1,
            "unit": "fr"
          },
          {
            "value": 1,
            "unit": "fr"
          },
          {
            "value": 1,
            "unit": "fr"
          },
          {
            "value": 0.5,
            "unit": "fr"
          }
        ],
        "columns": [
          {
            "value": 1,
            "unit": "fr"
          },
          {
            "value": 0.5,
            "unit": "fr"
          },
          {
            "value": 150,
            "unit": "px"
          },
          {
            "value": "10px, 1fr",
            "unit": "minmax"
          },
          {
            "value": "10%, 20px",
            "unit": "minmax"
          }
        ],
        "areas": [
          "header header header header header",
          "baner baner baner baner baner",
          "main main main image sidebar",
          "main main main . sidebar",
          "main main main . sidebar",
          "footer footer footer footer footer"
        ],
        "blocks": [
          {
            "blockName": "HEADER",
            "contents": {
              "type": "text",
              "value": "THIS IS HEADER"
            },
            "styles": {
              "color": "white",
              "gridArea": "header",
              "backgroundColor": "silver",
              "textAlign": "center"
            }
          },
          {
            "blockName": "API_EPISODE_LIST",
            "contents": {
              "type": "text",
              "endpoint": "/episode"
            },
            "styles": {
              "color": "white",
              "gridArea": "baner",
              "backgroundColor": "silver",
              "textAlign": "center"
            }
          },
          {
            "blockName": "TITLE",
            "contents": {
              "type": "text",
              "value": "THIS IS CARD SIDEBAR!!!"
            },
            "styles": {
              "color": "white",
              "gridArea": "sidebar",
              "backgroundColor": "gold",
              "textAlign": "center"
            }
          },
          {
            "blockName": "TITLE",
            "contents": {
              "type": "text",
              "value": "THIS IS CARD FOOTER!!!"
            },
            "styles": {
              "color": "white",
              "gridArea": "footer",
              "backgroundColor": "tomato",
              "textAlign": "center"
            }
          },
          {
            "blockName": "TITLE",
            "contents": {
              "type": "text",
              "value": "THIS IS CARD MAIN!!!"
            },
            "styles": {
              "color": "white",
              "gridArea": "main",
              "backgroundColor": "pink",
              "textAlign": "center"
            }
          },
          {
            "blockName": "API_IMAGE",
            "contents": {
              "type": "api",
              "value": "https://api.thecatapi.com/v1/images/search?size=full"
            },
            "styles": {
              "gridArea": "image",
              "width": "-webkit-fill-available",
              "objectFit": "contain"
            }
          }
        ]
      }
    ]
  }
}